Metadata-Version: 2.4
Name: iflow-mcp_excel-edit-server
Version: 0.1.3
Summary: A Model Context Protocol server providing excel edit capability
Author: iflow team
License: MIT
Keywords: automation,excel,llm,mcp
Classifier: Development Status :: 4 - Beta
Classifier: Intended Audience :: Developers
Classifier: License :: OSI Approved :: MIT License
Classifier: Programming Language :: Python :: 3
Classifier: Programming Language :: Python :: 3.10
Classifier: Programming Language :: Python :: 3.11
Classifier: Programming Language :: Python :: 3.12
Requires-Python: ==3.12.7
Requires-Dist: mcp[cli]>=1.12.4
Requires-Dist: openpyxl>=3.1.5
Requires-Dist: pandas>=2.3.1
Requires-Dist: pillow>=11.3.0
Requires-Dist: pycel>=1.0b30
